LICENSE
MANIFEST.in
README.rst
integration_test.py
setup.py
pyoembed/__init__.py
pyoembed/exceptions.py
pyoembed/utils.py
pyoembed.egg-info/PKG-INFO
pyoembed.egg-info/SOURCES.txt
pyoembed.egg-info/dependency_links.txt
pyoembed.egg-info/not-zip-safe
pyoembed.egg-info/requires.txt
pyoembed.egg-info/top_level.txt
pyoembed/data_types/__init__.py
pyoembed/data_types/link.py
pyoembed/data_types/photo.py
pyoembed/data_types/rich.py
pyoembed/data_types/video.py
pyoembed/parsers/__init__.py
pyoembed/parsers/json_parser.py
pyoembed/parsers/xml_parser.py
pyoembed/providers/__init__.py
pyoembed/providers/autodiscover.py
pyoembed/providers/bliptv.py
pyoembed/providers/deviantart.py
pyoembed/providers/dotsub.py
pyoembed/providers/geographorguk.py
pyoembed/providers/geohlippde.py
pyoembed/providers/imgur.py
pyoembed/providers/instagram.py
pyoembed/providers/mixcloud.py
pyoembed/providers/rdio.py
pyoembed/providers/sapopt.py
pyoembed/providers/spotify.py
pyoembed/providers/ustreamtv.py
pyoembed/tests/__init__.py
pyoembed/tests/test_data_types.py
pyoembed/tests/test_main.py
pyoembed/tests/test_utils.py
pyoembed/tests/parsers/__init__.py
pyoembed/tests/parsers/test_json_parser.py
pyoembed/tests/parsers/test_parsers.py
pyoembed/tests/parsers/test_xml_parser.py
pyoembed/tests/providers/__init__.py
pyoembed/tests/providers/test_autodiscover.py
pyoembed/tests/providers/test_main.py