Metadata-Version: 1.1
Name: pyoembed
Version: 0.1.2
Summary: A Python library for oEmbed that supports auto-discovered and manually included providers.
Home-page: UNKNOWN
Author: Rafael Goncalves Martins
Author-email: rafael@rafaelmartins.eng.br
License: BSD
Platform: any
Classifier: Development Status :: 3 - Alpha
Classifier: License :: OSI Approved :: BSD License
Classifier: Operating System :: OS Independent
Classifier: Programming Language :: Python :: 2
